asgi_lifecycle/__init__.py
asgi_lifecycle/lifespan.py
asgi_lifecycle/middleware.py
asgi_lifecycle-0.0.2.dist-info/METADATA
asgi_lifecycle-0.0.2.dist-info/WHEEL
asgi_lifecycle-0.0.2.dist-info/RECORD
