Metadata-Version: 2.4
Name: asgi-lifecycle
Version: 0.0.2
Summary: Flexible ASGI application lifecycle management for Python web frameworks.
Author-email: Tarek Sanger <tarek.sanger@me.com>
License: MIT
Keywords: asgi,celery,django,fastapi,hooks,lifecycle,lifespan,middleware,shutdown,starlette,startup
Classifier: Framework :: Django
Classifier: Framework :: FastAPI
Classifier: Intended Audience :: Developers
Classifier: License :: OSI Approved :: MIT License
Classifier: Operating System :: OS Independent
Classifier: Programming Language :: Python :: 3
Classifier: Programming Language :: Python :: 3.9
Classifier: Programming Language :: Python :: 3.10
Classifier: Programming Language :: Python :: 3.11
Classifier: Programming Language :: Python :: 3.12
Classifier: Topic :: Internet :: WWW/HTTP :: WSGI :: Middleware
Classifier: Topic :: Software Development :: Libraries :: Python Modules
Requires-Python: >=3.9
